{"paper": "paper.md", "sections_processed": 6, "triplets": [["pipeline", "data_loading", {"label": "step_1"}], ["pipeline", "preprocessing", {"label": "step_2"}], ["pipeline", "training", {"label": "step_3"}], ["pipeline", "evaluation", {"label": "step_4"}], ["training", "pruning", {"label": "requires"}], ["training", "parameter-efficient_fine_tuning", {"label": "requires"}], ["pruning", "pruning_ratio", {"label": "has_config"}], ["pruning_ratio", "0.6", {"label": "typically_uses"}], ["pruning_ratio", "0.7", {"label": "typically_uses"}], ["pruning", "task_performance", {"label": "evaluated_by"}], ["pruning", "inference_speed", {"label": "evaluated_by"}], ["pruning", "memory_usage", {"label": "evaluated_by"}], ["parameter-efficient_fine_tuning", "task_performance", {"label": "evaluated_by"}], ["parameter-efficient_fine_tuning", "inference_speed", {"label": "evaluated_by"}], ["parameter-efficient_fine_tuning", "memory_usage", {"label": "evaluated_by"}], ["parameter-efficient_fine_tuning", "adapter", {"label": "requires"}], ["adapter", "adapter_rank", {"label": "has_config"}], ["adapter", "adapter_dimensions", {"label": "has_config"}], ["structured_pruning", "block_based_pruning", {"label": "typically_uses"}], ["structured_pruning", "pruning_ratio", {"label": "has_config"}], ["structured_pruning", "inference_speed", {"label": "evaluated_by"}], ["structured_pruning", "memory_usage", {"label": "evaluated_by"}], ["structured_pruning", "task_performance", {"label": "evaluated_by"}], ["structured_pruning", "training_convergence_time", {"label": "evaluated_by"}], ["parameter-efficient_fine_tuning", "training_convergence_time", {"label": "evaluated_by"}], ["training", "structured_pruning", {"label": "requires"}], ["training", "self_distillation", {"label": "requires"}], ["self_distillation", "task_performance", {"label": "evaluated_by"}], ["self_distillation", "memory_usage", {"label": "evaluated_by"}], ["pipeline", "training", {"label": "step_1"}], ["additive_methods", "low_rank_decomposition", {"label": "typically_uses"}], ["additive_methods", "low_rank_rank", {"label": "has_config"}], ["low_rank_rank", "8", {"label": "typically_uses"}], ["dynamic_methods", "adaptive_parameter_adjustment", {"label": "requires"}], ["adaptive_parameter_tuning", "pruning", {"label": "requires"}], ["adaptive_parameter_tuning", "parameter-efficient_fine_tuning", {"label": "requires"}], ["adaptive_parameter_tuning", "inference_speed", {"label": "evaluated_by"}], ["adaptive_parameter_tuning", "memory_usage", {"label": "evaluated_by"}], ["adaptive_parameter_tuning", "task_performance", {"label": "evaluated_by"}], ["adaptive_parameter_tuning", "training_convergence_time", {"label": "evaluated_by"}], ["pipeline", "compression", {"label": "step_2"}], ["pipeline", "evaluation", {"label": "step_3"}], ["compression", "structured_pruning", {"label": "typically_uses"}], ["compression", "unstructured_pruning", {"label": "typically_uses"}], ["compression", "quantization", {"label": "typically_uses"}], ["structured_pruning", "knowledge_distillation", {"label": "requires"}], ["quantization", "bit_width", {"label": "has_config"}], ["bit_width", "8", {"label": "typically_uses"}], ["bit_width", "4", {"label": "typically_uses"}], ["quantization", "memory_usage", {"label": "evaluated_by"}], ["quantization", "inference_speed", {"label": "evaluated_by"}], ["parameter-efficient_fine_tuning", "lora", {"label": "typically_uses"}], ["parameter-efficient_fine_tuning", "compacter", {"label": "typically_uses"}], ["parameter-efficient_fine_tuning", "pruning", {"label": "typically_uses"}], ["pruning", "salience_based_parameter_selection", {"label": "requires"}], ["structured_pruning", "sparsity_ratio", {"label": "requires"}], ["structured_pruning", "sparsity_ratio", {"label": "has_config"}], ["sparsity_ratio", "0.5", {"label": "typically_uses"}], ["parameter-efficient_fine_tuning", "low_rank_decomposition", {"label": "requires"}], ["low_rank_decomposition", "low_rank_rank", {"label": "has_config"}], ["dynamic_parameter_adjustment", "sparsity_ratio", {"label": "requires"}], ["dynamic_parameter_adjustment", "tuning_rank", {"label": "requires"}], ["training", "dynamic_parameter_adjustment", {"label": "requires"}], ["pipeline", "evaluation", {"label": "step_2"}], ["evaluation", "task_performance", {"label": "evaluated_by"}], ["evaluation", "inference_speed", {"label": "evaluated_by"}], ["evaluation", "memory_usage", {"label": "evaluated_by"}], ["evaluation", "training_convergence_time", {"label": "evaluated_by"}], ["evaluation", "training_time", {"label": "evaluated_by"}], ["parameter-efficient_fine_tuning", "training_time", {"label": "evaluated_by"}], ["dynamic_parameter_adjustment", "task_performance", {"label": "evaluated_by"}], ["dynamic_parameter_adjustment", "training_convergence_time", {"label": "evaluated_by"}], ["training", "parameter_efficient_fine_tuning", {"label": "typically_uses"}], ["parameter_efficient_fine_tuning", "pruning", {"label": "requires"}], ["parameter_efficient_fine_tuning", "parameter_tuning", {"label": "requires"}], ["pruning", "binary_pruning_masks", {"label": "typically_uses"}], ["pruning", "sparsity_ratio", {"label": "has_config"}], ["parameter_tuning", "dynamic_rank_adjustment", {"label": "requires"}], ["parameter_tuning", "dynamic_rank", {"label": "typically_uses"}], ["dynamic_rank", "8", {"label": "typically_uses"}], ["parameter_efficient_fine_tuning", "adapters", {"label": "typically_uses"}], ["apt_adapter", "binary_pruning_masks", {"label": "requires"}], ["apt_adapter", "dynamic_rank", {"label": "requires"}], ["parameter_efficient_fine_tuning", "apt_adapter", {"label": "typically_uses"}], ["binary_pruning_masks", "0", {"label": "typically_uses"}], ["binary_pruning_masks", "1", {"label": "typically_uses"}], ["pipeline", "add_adapters", {"label": "step_2"}], ["adapters", "multi_head_attention", {"label": "typically_uses"}], ["adapters", "feed_forward_network", {"label": "typically_uses"}], ["adaptive_pruning", "outlier_aware_salience_scoring", {"label": "requires"}], ["outlier_aware_salience_scoring", "activation_gradients", {"label": "requires"}], ["outlier_aware_salience_scoring", "kurtosis", {"label": "requires"}], ["adaptive_pruning", "binary_pruning_masks", {"label": "requires"}], ["outlier_aware_salience_scoring", "batch_summing", {"label": "typically_uses"}], ["batch_summing", "enabled", {"label": "has_config"}], ["adaptive_pruning", "sparsity_ratio", {"label": "has_config"}], ["training", "adaptive_pruning", {"label": "step_2"}], ["adaptive_pruning", "training_stability", {"label": "evaluated_by"}], ["adaptive_pruning", "memory_usage", {"label": "evaluated_by"}], ["adaptive_pruning", "task_performance", {"label": "evaluated_by"}], ["pipeline", "evaluate_efficiency_metrics", {"label": "step_3"}], ["evaluate_efficiency_metrics", "memory_usage", {"label": "evaluated_by"}], ["evaluate_efficiency_metrics", "inference_speed", {"label": "evaluated_by"}], ["evaluate_efficiency_metrics", "training_time", {"label": "evaluated_by"}], ["salience_scoring", "activation_gradients", {"label": "requires"}], ["salience_scoring", "activation_kurtosis", {"label": "requires"}], ["parameter_pruning", "mha_head_pruning", {"label": "requires"}], ["parameter_pruning", "ffn_neuron_pruning", {"label": "requires"}], ["parameter_pruning", "hidden_dimension_reduction", {"label": "requires"}], ["parameter_pruning", "knapsack_optimization", {"label": "typically_uses"}], ["parameter_pruning", "binary_search", {"label": "typically_uses"}], ["parameter_pruning", "sparsity_ratio", {"label": "has_config"}], ["adaptive_fine_tuning", "dynamic_parameter_adjustment", {"label": "requires"}], ["adaptive_fine_tuning", "parameter_efficient_fine_tuning", {"label": "requires"}], ["pipeline", "salience_scoring", {"label": "step_1"}], ["pipeline", "parameter_pruning", {"label": "step_2"}], ["pipeline", "adaptive_fine_tuning", {"label": "step_3"}], ["evaluation", "model_size", {"label": "evaluated_by"}], ["salience_scoring", "parameter_summation", {"label": "typically_uses"}], ["parameter_adjustment", "sorted_salience", {"label": "requires"}], ["parameter_adjustment", "budget_parameter", {"label": "requires"}], ["parameter_adjustment", "dynamic_rank", {"label": "typically_uses"}], ["dynamic_rank", "floor_operation", {"label": "typically_uses"}], ["parameter_adjustment", "top_selection", {"label": "typically_uses"}], ["top_selection", "0.5", {"label": "has_config"}], ["pipeline", "parameter_adjustment", {"label": "step_2"}], ["evaluate_efficiency_metrics", "task_performance", {"label": "evaluated_by"}], ["evaluate_efficiency_metrics", "training_costs", {"label": "evaluated_by"}], ["parameter_initialization", "gaussian_initialization", {"label": "typically_uses"}], ["parameter_initialization", "zero_initialization", {"label": "typically_uses"}], ["gaussian_initialization", "mean_0", {"label": "has_config"}], ["gaussian_initialization", "variance_squared", {"label": "has_config"}], ["self_knowledge_distillation", "student_teacher_duplication", {"label": "requires"}], ["self_knowledge_distillation", "shared_parameters", {"label": "requires"}], ["distillation_objective", "mse_loss", {"label": "typically_uses"}], ["moving_term", "linear_schedule", {"label": "has_config"}], ["moving_term", "0_to_1_range", {"label": "has_config"}], ["layer_mapping_function", "non_pruned_layer_matching", {"label": "requires"}], ["layer_transformation", "identity_matrix_initialization", {"label": "typically_uses"}], ["self_knowledge_distillation", "training_time", {"label": "evaluated_by"}], ["self_knowledge_distillation", "memory_usage", {"label": "evaluated_by"}], ["block_sampling", "t_count", {"label": "has_config"}], ["block_sampling", "random_sampling", {"label": "typically_uses"}], ["pipeline", "knowledge_distillation", {"label": "step_2"}], ["knowledge_distillation", "self_knowledge_distillation", {"label": "requires"}], ["evaluation_protocol", "task_performance", {"label": "evaluated_by"}], ["evaluation_protocol", "training_costs", {"label": "evaluated_by"}]], "hypernode_store": {}, "stats": {"total_triplets": 147, "api_cost": 1.30007}}